Metadata-Version: 2.1
Name: hmm-kit
Version: 0.3.0
Summary: Python toolkit for unsupervised learning of sequences of observations using HMM
Home-page: https://github.com/eranroz/hmm
Author: Eran Rosenthal
Author-email: eranroz@cs.huji.ac.il
License: MIT License
Platform: UNKNOWN
Classifier: License :: OSI Approved :: MIT License
Classifier: Development Status :: 4 - Beta
Classifier: Operating System :: OS Independent
Classifier: Intended Audience :: Science/Research
